utilities/__init__.py
utilities/playwright_utils.py
meyi_automation_utils-0.1.0.dist-info/METADATA
meyi_automation_utils-0.1.0.dist-info/WHEEL
meyi_automation_utils-0.1.0.dist-info/top_level.txt
meyi_automation_utils-0.1.0.dist-info/RECORD
