Metadata-Version: 2.4
Name: meyi-automation-utils
Version: 0.1.0
Summary: Reusable Playwright automation utilities
Author: Santhanalakshmi R
Requires-Python: >=3.9
Requires-Dist: playwright
Requires-Dist: pytest
Dynamic: author
Dynamic: requires-python
